octobot_evaluators/__init__.pxd
octobot_evaluators/__init__.py
octobot_evaluators/constants.py
octobot_evaluators/enums.py
octobot_evaluators/errors.py
octobot_evaluators/octobot_channel_consumer.cp38-win_amd64.pyd
octobot_evaluators/octobot_channel_consumer.pxd
octobot_evaluators/octobot_channel_consumer.py
octobot_evaluators/api/__init__.py
octobot_evaluators/api/evaluators.py
octobot_evaluators/api/initialization.py
octobot_evaluators/api/inspection.py
octobot_evaluators/api/matrix.py
octobot_evaluators/evaluators/TA_evaluator.py
octobot_evaluators/evaluators/__init__.pxd
octobot_evaluators/evaluators/__init__.py
octobot_evaluators/evaluators/abstract_evaluator.py
octobot_evaluators/evaluators/abstract_util.py
octobot_evaluators/evaluators/evaluator_factory.cp38-win_amd64.pyd
octobot_evaluators/evaluators/evaluator_factory.pxd
octobot_evaluators/evaluators/evaluator_factory.py
octobot_evaluators/evaluators/realtime_evaluator.py
octobot_evaluators/evaluators/scripted_evaluator.py
octobot_evaluators/evaluators/social_evaluator.py
octobot_evaluators/evaluators/strategy_evaluator.py
octobot_evaluators/evaluators/channel/__init__.pxd
octobot_evaluators/evaluators/channel/__init__.py
octobot_evaluators/evaluators/channel/evaluator_channel.cp38-win_amd64.pyd
octobot_evaluators/evaluators/channel/evaluator_channel.pxd
octobot_evaluators/evaluators/channel/evaluator_channel.py
octobot_evaluators/evaluators/channel/evaluators.cp38-win_amd64.pyd
octobot_evaluators/evaluators/channel/evaluators.pxd
octobot_evaluators/evaluators/channel/evaluators.py
octobot_evaluators/matrix/__init__.pxd
octobot_evaluators/matrix/__init__.py
octobot_evaluators/matrix/matrices.cp38-win_amd64.pyd
octobot_evaluators/matrix/matrices.pxd
octobot_evaluators/matrix/matrices.py
octobot_evaluators/matrix/matrix.cp38-win_amd64.pyd
octobot_evaluators/matrix/matrix.pxd
octobot_evaluators/matrix/matrix.py
octobot_evaluators/matrix/matrix_manager.cp38-win_amd64.pyd
OctoBot_Evaluators-1.8.7.dist-info/LICENSE
OctoBot_Evaluators-1.8.7.dist-info/METADATA
OctoBot_Evaluators-1.8.7.dist-info/WHEEL
OctoBot_Evaluators-1.8.7.dist-info/top_level.txt
OctoBot_Evaluators-1.8.7.dist-info/RECORD
